ideal_genom/__init__.py
ideal_genom/__main__.py
ideal_genom/core/cli.py
ideal_genom/core/config.py
ideal_genom/core/environment.py
ideal_genom/core/executor.py
ideal_genom/core/get_examples.py
ideal_genom/core/get_references.py
ideal_genom/core/pipeline.py
ideal_genom/core/utils.py
ideal_genom/data/ld_regions_files/high-LD-regions_GRCH38.txt
ideal_genom/gwas/__init__.py
ideal_genom/gwas/gen_linear_mix_model.py
ideal_genom/gwas/gen_linear_model.py
ideal_genom/gwas/preparatory.py
ideal_genom/population/__init__.py
ideal_genom/population/fst_stats.py
ideal_genom/population/projection.py
ideal_genom/post_imputation/vcf_process.py
ideal_genom/post_imputation/vcf_to_plink.py
ideal_genom/qc/__init__.py
ideal_genom/qc/ancestry_qc.py
ideal_genom/qc/sample_qc.py
ideal_genom/qc/variant_qc.py
ideal_genom/utilities/annotations.py
ideal_genom/utilities/api_client.py
ideal_genom/utilities/power_comp.py
ideal_genom/visualizations/manhattan_type.py
ideal_genom/visualizations/plots.py
ideal_genom/visualizations/zoom_heatmap.py
ideal_genom-1.1.0.dist-info/METADATA
ideal_genom-1.1.0.dist-info/WHEEL
ideal_genom-1.1.0.dist-info/entry_points.txt
ideal_genom-1.1.0.dist-info/licenses/LICENSE
ideal_genom-1.1.0.dist-info/RECORD
