Metadata-Version: 2.4
Name: ideal-genom
Version: 1.1.0
Summary: package to run a genotype quality control pipeline
License: MIT
License-File: LICENSE
Author: Luis Giraldo González
Author-email: luisggon@protonmail.com
Requires-Python: >=3.11,<3.13
Classifier: License :: OSI Approved :: MIT License
Classifier: Operating System :: OS Independent
Classifier: Programming Language :: Python :: 3
Classifier: Programming Language :: Python :: 3.11
Classifier: Programming Language :: Python :: 3.12
Requires-Dist: PyYAML (>=6.0,<7.0.0)
Requires-Dist: gtfparse (>=2.5.0,<3.0.0)
Requires-Dist: ipywidgets (>=8.1.5,<9.0.0)
Requires-Dist: jupyter (>=1.1.1,<2.0.0)
Requires-Dist: llvmlite (>=0.43.0,<1.0.0)
Requires-Dist: matplotlib (>=3.8.3,<4.0.0)
Requires-Dist: numpy (<2)
Requires-Dist: openpyxl (>=3.1.5,<4.0.0)
Requires-Dist: pandas (>=2.2.1,<3.0.0)
Requires-Dist: psutil (>=5.9.8,<6.0.0)
Requires-Dist: pyensembl (>=2.3.13,<3.0.0)
Requires-Dist: requests (>=2.31.0,<3.0.0)
Requires-Dist: scipy (>=1.12.0,<2.0.0)
Requires-Dist: seaborn (>=0.13.2,<1.0.0)
Requires-Dist: textalloc (>=1.2.1,<2.0.0)
Requires-Dist: umap-learn (>=0.5.6,<1.0.0)
Project-URL: Homepage, https://github.com/LuisGiraldo86/IDEAL-GENOM
Project-URL: Issues, https://github.com/LuisGiraldo86/IDEAL-GENOM/issues
